{
  "id": "node_modules/format/Readme",
  "title": "format",
  "description": "printf, sprintf, and vsprintf for JavaScript",
  "source": "@site/node_modules/format/Readme.md",
  "sourceDirName": "node_modules/format",
  "slug": "/node_modules/format/",
  "permalink": "/node_modules/format/",
  "draft": false,
  "unlisted": false,
  "editUrl": "https://github.com/facebook/docusaurus/tree/main/packages/create-docusaurus/templates/shared/node_modules/format/Readme.md",
  "tags": [],
  "version": "current",
  "frontMatter": {}
}