{
  "id": "node_modules/proto-list/README",
  "title": "README",
  "description": "A list of objects, bound by their prototype chain.",
  "source": "@site/docs/node_modules/proto-list/README.md",
  "sourceDirName": "node_modules/proto-list",
  "slug": "/node_modules/proto-list/",
  "permalink": "/physical-ai-textbook/node_modules/proto-list/",
  "draft": false,
  "unlisted": false,
  "editUrl": "https://github.com/IlsaFatima1/physical-ai-textbook/tree/main/docs/node_modules/proto-list/README.md",
  "tags": [],
  "version": "current",
  "frontMatter": {}
}